funfile/__init__.py
funfile/funos.py
funfile/compress/__init__.py
funfile/compress/allfile.py
funfile/compress/tarfile.py
funfile/compress/utils.py
funfile/compress/zipfile.py
funfile/file/__init__.py
funfile/file/concurrent.py
funfile/file/core.py
funfile/pickle/__init__.py
funfile/pickle/core.py
funfile-1.0.15.dist-info/METADATA
funfile-1.0.15.dist-info/WHEEL
funfile-1.0.15.dist-info/top_level.txt
funfile-1.0.15.dist-info/RECORD
