Metadata-Version: 2.1
Name: funfile
Version: 1.0.15
Summary: funfile
Author-email: niuliangtao <farfarfun@qq.com>
Requires-Python: >=3.7
Requires-Dist: funutil>=1.0.15
Requires-Dist: tqdm>=4.66.5
